sidanwebframework/__init__.py
sidanwebframework/sidanwebframework.py
sidanwebframework-1.0.2.dist-info/LICENSE
sidanwebframework-1.0.2.dist-info/METADATA
sidanwebframework-1.0.2.dist-info/WHEEL
sidanwebframework-1.0.2.dist-info/top_level.txt
sidanwebframework-1.0.2.dist-info/RECORD
