Metadata-Version: 2.1
Name: sidanwebframework
Version: 1.0.2
Summary: sidanwebframework
Home-page: https://bitbucket.org/muhammedsidan/sidanwebframework/
Author: sidan
License: UNKNOWN
Platform: UNKNOWN
Classifier: Programming Language :: Python :: 3
Classifier: License :: OSI Approved :: MIT License
Classifier: Operating System :: OS Independent
